spire/__init__.py
spire/xls/AddtionalFormatWrapper.py
spire/xls/Average.py
spire/xls/CellBaseStyle.py
spire/xls/CellBorder.py
spire/xls/CellRange.py
spire/xls/CellStyle.py
spire/xls/CellStyleFlag.py
spire/xls/CellStyleObject.py
spire/xls/CellValueChangedEventArgs.py
spire/xls/CellValueChangedEventHandler.py
spire/xls/ColorScale.py
spire/xls/CommentsRange.py
spire/xls/CommonWrapper.py
spire/xls/ConverterSetting.py
spire/xls/DBConnection.py
spire/xls/DVAspect.py
spire/xls/DataBar.py
spire/xls/DocumentProperty.py
spire/xls/Excel2016Charttype.py
spire/xls/ExcelAddInFunction.py
spire/xls/ExcelComment.py
spire/xls/ExcelCommentObject.py
spire/xls/ExcelFont.py
spire/xls/ExcelGradient.py
spire/xls/ExcelInterior.py
spire/xls/ExcelPicture.py
spire/xls/ExportTableOptions.py
spire/xls/ExternalConnection.py
spire/xls/ExternalLink.py
spire/xls/FileFormat.py
spire/xls/Font.py
spire/xls/FontArrayWrapper.py
spire/xls/FontWrapper.py
spire/xls/Format3D.py
spire/xls/GeomertyAdjustValue.py
spire/xls/GetText.py
spire/xls/GoalSeek.py
spire/xls/GoalSeekResult.py
spire/xls/GradientArrayWrapper.py
spire/xls/GradientStops.py
spire/xls/GradientType.py
spire/xls/GroupShape.py
spire/xls/HPageBreak.py
spire/xls/HTMLOptions.py
spire/xls/HyperLink.py
spire/xls/LOGFONT.py
spire/xls/MsoPathInfo.py
spire/xls/OColor.py
spire/xls/OdsPageBackground.py
spire/xls/PageColRow.py
spire/xls/PageSetup.py
spire/xls/PaperSizeEntry.py
spire/xls/PicStretch.py
spire/xls/PicTile.py
spire/xls/QueryTableXls.py
spire/xls/RTFCommentArray.py
spire/xls/RTFStringArray.py
spire/xls/RangeRichTextString.py
spire/xls/ReferRangeArea.py
spire/xls/RichText.py
spire/xls/RichTextObject.py
spire/xls/RichTextShape.py
spire/xls/RichTextString.py
spire/xls/RtfTextWriter.py
spire/xls/SaveShapeTypeOption.py
spire/xls/ShapeGeomPath.py
spire/xls/ShapeGlow.py
spire/xls/ShapeReflection.py
spire/xls/ShapeSegmentPath.py
spire/xls/StringUtil.py
spire/xls/StyleArrayWrapper.py
spire/xls/TextBoxShapeBase.py
spire/xls/TextSaveOptions.py
spire_xls-15.7.1.dist-info/METADATA
spire_xls-15.7.1.dist-info/WHEEL
spire_xls-15.7.1.dist-info/top_level.txt
spire_xls-15.7.1.dist-info/RECORD
